feature_toggle_ui/__init__.py
feature_toggle_ui/__main__.py
feature_toggle_ui-0.0.1.dist-info/LICENSE
feature_toggle_ui-0.0.1.dist-info/METADATA
feature_toggle_ui-0.0.1.dist-info/WHEEL
feature_toggle_ui-0.0.1.dist-info/top_level.txt
feature_toggle_ui-0.0.1.dist-info/RECORD
