Metadata-Version: 2.1
Name: feature-toggle-ui
Version: 0.0.1
Summary: A small example package
Home-page: 
Author: Dofamin
Author-email: 
License: unlicensed
Classifier: Programming Language :: Python :: 3
Classifier: Operating System :: OS Independent
Requires-Python: >=3.10
License-File: LICENSE
Requires-Dist: setuptools >=68.2.2
Requires-Dist: pytz >=2023.3.post1
Requires-Dist: requests >=2.31.0
Requires-Dist: urllib3 >=2.0.6
